be/__init__.py
be/api/__init__.py
be/api/execute.py
app.json
avyas_aurica_base_apps_agent_cli-1.0.2.dist-info/METADATA
avyas_aurica_base_apps_agent_cli-1.0.2.dist-info/WHEEL
avyas_aurica_base_apps_agent_cli-1.0.2.dist-info/RECORD
