Metadata-Version: 2.4
Name: avyas-aurica-base-apps-agent-cli
Version: 1.0.2
Summary: Aurica app: agent-cli
Requires-Python: >=3.11
Requires-Dist: fastapi>=0.104.0
Requires-Dist: uvicorn>=0.24.0
